hgp/__init__.py
hgp/match/__init__.py
hgp/match/__main__.py
hgp/match/main.py
hgp/match/matching.py
hgpmatch-1.0.1.data/scripts/hgpmatch
tests/__init__.py
tests/match/__init__.py
tests/match/test_main.py
tests/match/test_match.py
tests/match/util.py
hgpmatch-1.0.1.dist-info/LICENSE
hgpmatch-1.0.1.dist-info/METADATA
hgpmatch-1.0.1.dist-info/WHEEL
hgpmatch-1.0.1.dist-info/top_level.txt
hgpmatch-1.0.1.dist-info/RECORD
